apinator_databricks/__init__.py
apinator_databricks/common.py
apinator_databricks/_common/api.py
apinator_databricks/_common/model.py
apinator_databricks/marketplace_provider/__init__.py
apinator_databricks/marketplace_provider/api.py
apinator_databricks/marketplace_provider/model.py
apinator_databricks/unity_catalog/__init__.py
apinator_databricks/unity_catalog/api.py
apinator_databricks/unity_catalog/model.py
apinator_databricks-0.1.0.dist-info/LICENSE
apinator_databricks-0.1.0.dist-info/WHEEL
apinator_databricks-0.1.0.dist-info/METADATA
apinator_databricks-0.1.0.dist-info/RECORD
