Metadata-Version: 2.1
Name: apinator-databricks
Version: 0.1.0
Summary: APInator bindings for Databricks API
Author-email: Rearc Data <data@rearc.io>
Requires-Python: >=3.7
Requires-Dist: apinator~=0.1.0
Requires-Dist: pytest ; extra == "test"
Requires-Dist: pytest-cov ; extra == "test"
Requires-Dist: responses ; extra == "test"
Project-URL: Home, https://github.com/rearc-data/apinator-databricks
Provides-Extra: test
